ShenruqianchuJavaWeb/README.md
ShenruqianchuJavaWeb/__init__.py
ShenruqianchuJavaWeb/__main__.py
ShenruqianchuJavaWeb/file.epub
ShenruqianchuJavaWeb/index.html
ShenruqianchuJavaWeb/css/__init__.py
ShenruqianchuJavaWeb/css/annotations.css
ShenruqianchuJavaWeb/css/main.css
ShenruqianchuJavaWeb/css/normalize.css
ShenruqianchuJavaWeb/css/popup.css
ShenruqianchuJavaWeb/font/__init__.py
ShenruqianchuJavaWeb/font/fontello.eot
ShenruqianchuJavaWeb/font/fontello.svg
ShenruqianchuJavaWeb/font/fontello.ttf
ShenruqianchuJavaWeb/font/fontello.woff
ShenruqianchuJavaWeb/img/__init__.py
ShenruqianchuJavaWeb/img/annotator-glyph-sprite.png
ShenruqianchuJavaWeb/img/annotator-icon-sprite.png
ShenruqianchuJavaWeb/img/apple-touch-icon.png
ShenruqianchuJavaWeb/img/cancelfullscreen.png
ShenruqianchuJavaWeb/img/close.png
ShenruqianchuJavaWeb/img/fullscreen.png
ShenruqianchuJavaWeb/img/loader.gif
ShenruqianchuJavaWeb/img/menu-icon.png
ShenruqianchuJavaWeb/img/save.png
ShenruqianchuJavaWeb/img/saved.png
ShenruqianchuJavaWeb/img/settings-s.png
ShenruqianchuJavaWeb/img/settings.png
ShenruqianchuJavaWeb/img/star.png
ShenruqianchuJavaWeb/js/__init__.py
ShenruqianchuJavaWeb/js/epub.js
ShenruqianchuJavaWeb/js/epub.min.js
ShenruqianchuJavaWeb/js/epub.min.map
ShenruqianchuJavaWeb/js/hooks.min.js
ShenruqianchuJavaWeb/js/hooks.min.map
ShenruqianchuJavaWeb/js/reader.js
ShenruqianchuJavaWeb/js/reader.js.map
ShenruqianchuJavaWeb/js/reader.min.js
ShenruqianchuJavaWeb/js/reader.min.map
ShenruqianchuJavaWeb/js/hooks/__init__.py
ShenruqianchuJavaWeb/js/hooks/extensions/__init__.py
ShenruqianchuJavaWeb/js/hooks/extensions/highlight.js
ShenruqianchuJavaWeb/js/libs/__init__.py
ShenruqianchuJavaWeb/js/libs/jquery.min.js
ShenruqianchuJavaWeb/js/libs/localforage.min.js
ShenruqianchuJavaWeb/js/libs/screenfull.js
ShenruqianchuJavaWeb/js/libs/screenfull.min.js
ShenruqianchuJavaWeb/js/libs/zip.min.js
ShenruqianchuJavaWeb/js/plugins/__init__.py
ShenruqianchuJavaWeb/js/plugins/hypothesis.js
shenruqianchu_java_web-2024.3.3.0.dist-info/METADATA
shenruqianchu_java_web-2024.3.3.0.dist-info/WHEEL
shenruqianchu_java_web-2024.3.3.0.dist-info/entry_points.txt
shenruqianchu_java_web-2024.3.3.0.dist-info/top_level.txt
shenruqianchu_java_web-2024.3.3.0.dist-info/RECORD
